LICENSE
README.md
setup.py
coinzdense/__init__.py
coinzdense.egg-info/PKG-INFO
coinzdense.egg-info/SOURCES.txt
coinzdense.egg-info/dependency_links.txt
coinzdense.egg-info/requires.txt
coinzdense.egg-info/top_level.txt
coinzdense/layerzero/__init__.py
coinzdense/layerzero/level.py
coinzdense/layerzero/onetime.py
coinzdense/layerzero/wif.py