Metadata-Version: 2.1
Name: coinzdense
Version: 0.1.2
Summary: Simple Post-Quantum Signature library
Home-page: https://github.com/pibara/coinzdense-python
Author: Rob J Meijer
Author-email: pibara@gmail.com
License: BSD
Keywords: signing postquantum blake2 merkletree ots
Platform: UNKNOWN
Classifier: Development Status :: 2 - Pre-Alpha
Classifier: Intended Audience :: Developers
Classifier: Topic :: Software Development :: Libraries
Classifier: Topic :: Security :: Cryptography
Classifier: License :: OSI Approved :: BSD License
Classifier: Programming Language :: Python :: 3
Classifier: Programming Language :: Python :: 3.8
Classifier: Programming Language :: Python :: 3.9
Classifier: Programming Language :: Python :: 3.10
Classifier: Operating System :: OS Independent
Classifier: Environment :: Other Environment
License-File: LICENSE
